test_version_powerhouse_helper/__init__.py
test_version_powerhouse_helper/__main__.py
test_version_powerhouse_helper/GameGooseKiller/font/UA Propisi.ttf
test_version_powerhouse_helper/GameGooseKiller/image/Farm-Goose.ico
test_version_powerhouse_helper/GameGooseKiller/image/background.png
test_version_powerhouse_helper/GameGooseKiller/image/bonus.png
test_version_powerhouse_helper/GameGooseKiller/image/boom.png
test_version_powerhouse_helper/GameGooseKiller/image/enemy.png
test_version_powerhouse_helper/GameGooseKiller/image/gameover.png
test_version_powerhouse_helper/GameGooseKiller/image/Goose/1-1.png
test_version_powerhouse_helper/GameGooseKiller/image/Goose/1-2.png
test_version_powerhouse_helper/GameGooseKiller/image/Goose/1-3.png
test_version_powerhouse_helper/GameGooseKiller/image/Goose/1-4.png
test_version_powerhouse_helper/GameGooseKiller/image/Goose/1-5.png
test_version_powerhouse_helper/GameGooseKiller/image/background/1-1.png
test_version_powerhouse_helper/GameGooseKiller/image/background/1-2.png
test_version_powerhouse_helper/GameGooseKiller/image/background/1-3.png
test_version_powerhouse_helper-1.data/data/test_version_powerhouse_helper/GameGooseKiller/font/UA Propisi.ttf
test_version_powerhouse_helper-1.data/data/test_version_powerhouse_helper/GameGooseKiller/image/Farm-Goose.ico
test_version_powerhouse_helper-1.data/data/test_version_powerhouse_helper/GameGooseKiller/image/background.png
test_version_powerhouse_helper-1.data/data/test_version_powerhouse_helper/GameGooseKiller/image/bonus.png
test_version_powerhouse_helper-1.data/data/test_version_powerhouse_helper/GameGooseKiller/image/boom.png
test_version_powerhouse_helper-1.data/data/test_version_powerhouse_helper/GameGooseKiller/image/enemy.png
test_version_powerhouse_helper-1.data/data/test_version_powerhouse_helper/GameGooseKiller/image/gameover.png
test_version_powerhouse_helper-1.data/data/test_version_powerhouse_helper/GameGooseKiller/image/Goose/1-1.png
test_version_powerhouse_helper-1.dist-info/LICENSE
test_version_powerhouse_helper-1.dist-info/METADATA
test_version_powerhouse_helper-1.dist-info/WHEEL
test_version_powerhouse_helper-1.dist-info/entry_points.txt
test_version_powerhouse_helper-1.dist-info/top_level.txt
test_version_powerhouse_helper-1.dist-info/RECORD
